flet_translator/__init__.py
flet_translator/tools/__init__.py
flet_translator/tools/translate_control_content.py
flet_translator/tools/translate_page.py
flet_translator/tools/translate_using_google.py
flet_translator/tools/translate_using_opusMT.py
flet_translator/utils/__init__.py
flet_translator/utils/allowed_props_to_translate.py
flet_translator/utils/google_supported_langaues.py
flet_translator/utils/is_rtl.py
flet_translator/utils/opusMT_supported_languages.py
flet_translator-1.2.6.dist-info/LICENSE
flet_translator-1.2.6.dist-info/METADATA
flet_translator-1.2.6.dist-info/WHEEL
flet_translator-1.2.6.dist-info/top_level.txt
flet_translator-1.2.6.dist-info/RECORD
