Metadata-Version: 2.1
Name: flet-translator
Version: 1.2.6
Summary: A package that help flet developers to make their apps support multiple languages
Home-page: https://github.com/SKbarbon/flet_translator
Author: SKbarbon
Classifier: Programming Language :: Python :: 3
Classifier: Operating System :: MacOS :: MacOS X
Classifier: Operating System :: Microsoft :: Windows
License-File: LICENSE
Requires-Dist: flet
Requires-Dist: sacremoses
Requires-Dist: deep-translator
